uvloop-0.20.0.dist-info/LICENSE-APACHE
uvloop-0.20.0.dist-info/RECORD
uvloop-0.20.0.dist-info/WHEEL
uvloop-0.20.0.dist-info/top_level.txt
uvloop-0.20.0.dist-info/METADATA
uvloop-0.20.0.dist-info/LICENSE-MIT
uvloop/cbhandles.pyx
uvloop/dns.pyx
uvloop/loop.pxd
uvloop/server.pyx
uvloop/errors.pyx
uvloop/sslproto.pyx
uvloop/_version.py
uvloop/pseudosock.pyx
uvloop/lru.pyx
uvloop/_noop.py
uvloop/request.pxd
uvloop/_testbase.py
uvloop/loop.pyi
uvloop/__init__.py
uvloop/request.pyx
uvloop/py.typed
uvloop/sslproto.pxd
uvloop/loop.cpython-311-darwin.so
uvloop/loop.pyx
uvloop/server.pxd
uvloop/cbhandles.pxd
uvloop/handles/pipe.pxd
uvloop/handles/basetransport.pyx
uvloop/handles/check.pyx
uvloop/handles/process.pxd
uvloop/handles/stream.pyx
uvloop/handles/timer.pxd
uvloop/handles/poll.pxd
uvloop/handles/tcp.pxd
uvloop/handles/udp.pxd
uvloop/handles/streamserver.pyx
uvloop/handles/idle.pyx
uvloop/handles/async_.pyx
uvloop/handles/fsevent.pyx
uvloop/handles/handle.pyx
uvloop/handles/fsevent.pxd
uvloop/handles/handle.pxd
uvloop/handles/async_.pxd
uvloop/handles/idle.pxd
uvloop/handles/streamserver.pxd
uvloop/handles/udp.pyx
uvloop/handles/tcp.pyx
uvloop/handles/poll.pyx
uvloop/handles/timer.pyx
uvloop/handles/stream.pxd
uvloop/handles/process.pyx
uvloop/handles/check.pxd
uvloop/handles/basetransport.pxd
uvloop/handles/pipe.pyx
uvloop/includes/consts.pxi
uvloop/includes/__init__.py
uvloop/includes/debug.pxd
uvloop/includes/flowcontrol.pxd
uvloop/includes/system.pxd
uvloop/includes/uv.pxd
uvloop/includes/python.pxd
uvloop/includes/stdlib.pxi
