Metadata-Version: 2.1
Name: uvloop
Version: 0.20.0
Summary: Fast implementation of asyncio event loop on top of libuv
Author-email: Yury Selivanov <yury@magic.io>
License: MIT License
Project-URL: github, https://github.com/MagicStack/uvloop
Keywords: asyncio,networking
Classifier: Development Status :: 5 - Production/Stable
Classifier: Framework :: AsyncIO
Classifier: Intended Audience :: Developers
Classifier: License :: OSI Approved :: Apache Software License
Classifier: License :: OSI Approved :: MIT License
Classifier: Operating System :: POSIX
Classifier: Operating System :: MacOS :: MacOS X
Classifier: Programming Language :: Python :: 3 :: Only
Classifier: Programming Language :: Python :: 3.8
Classifier: Programming Language :: Python :: 3.9
Classifier: Programming Language :: Python :: 3.10
Classifier: Programming Language :: Python :: 3.11
Classifier: Programming Language :: Python :: 3.12
Classifier: Programming Language :: Python :: Implementation :: CPython
Classifier: Topic :: System :: Networking
Requires-Python: >=3.8.0
License-File: LICENSE-APACHE
License-File: LICENSE-MIT
Provides-Extra: test
Requires-Dist: aiohttp>=3.8.1; python_version < "3.12" and extra == "test"
Requires-Dist: aiohttp==3.9.0b0; python_version >= "3.12" and extra == "test"
Requires-Dist: flake8~=5.0; extra == "test"
Requires-Dist: psutil; extra == "test"
Requires-Dist: pycodestyle~=2.9.0; extra == "test"
Requires-Dist: pyOpenSSL~=23.0.0; extra == "test"
Requires-Dist: mypy>=0.800; extra == "test"
Requires-Dist: Cython<0.30.0,>=0.29.36; extra == "test"
Provides-Extra: docs
Requires-Dist: Sphinx~=4.1.2; extra == "docs"
Requires-Dist: sphinxcontrib-asyncio~=0.3.0; extra == "docs"
Requires-Dist: sphinx_rtd_theme~=0.5.2; extra == "docs"
